{"_type":"export","__export_format":4,"__export_date":"2024-10-04T23:06:32.691Z","__export_source":"insomnia.desktop.app:v10.0.0","resources":[{"_id":"req_591ae89e20c04cd8b47e00c3d45c885a","parentId":"fld_a944cddf67824f2c9c3386fdfec23fd9","modified":1728081251603,"created":1728081172743,"url":"{{ _.base_url }}/login","name":"New Request","description":"","method":"POST","body":{"mimeType":"application/json","text":"{\n\t\"email\":\"adm@teste.com\",\n\t\"senha\":\"123456\"\n}"},"parameters":[],"headers":[{"name":"Content-Type","value":"application/json"},{"name":"User-Agent","value":"insomnia/10.0.0"}],"authentication":{},"metaSortKey":-1728081172743,"isPrivate":false,"pathParameters":[],"settingStoreCookies":true,"settingSendCookies":true,"settingDisableRenderRequestBody":false,"settingEncodeUrl":true,"settingRebuildPath":true,"settingFollowRedirects":"global","_type":"request"},{"_id":"fld_a944cddf67824f2c9c3386fdfec23fd9","parentId":"wrk_0a3c7bf00e4d47ed90e477db4d5e10bb","modified":1728081167345,"created":1728081167345,"name":"Usuário","description":"","environment":{},"environmentPropertyOrder":null,"metaSortKey":-1728081167345,"_type":"request_group"},{"_id":"wrk_0a3c7bf00e4d47ed90e477db4d5e10bb","parentId":null,"modified":1728080864808,"created":1728080864808,"name":"minimal-api-c#","description":"","scope":"collection","_type":"workspace"},{"_id":"env_d72e3847fc3a4de06aecc05b6b2711c097371175","parentId":"wrk_0a3c7bf00e4d47ed90e477db4d5e10bb","modified":1728081126057,"created":1728080864810,"name":"Base Environment","data":{"base_url":"http://localhost:5175"},"dataPropertyOrder":{"&":["base_url"]},"color":null,"isPrivate":false,"metaSortKey":1728080864810,"_type":"environment"},{"_id":"jar_d72e3847fc3a4de06aecc05b6b2711c097371175","parentId":"wrk_0a3c7bf00e4d47ed90e477db4d5e10bb","modified":1728080864811,"created":1728080864811,"name":"Default Jar","cookies":[],"_type":"cookie_jar"}]}